morphon/__init__.py
morphon/lib.py
morphon/morph.py
morphon/nodes.py
morphon/swc.py
morphon-0.0.8.data/scripts/mcheck
morphon-0.0.8.data/scripts/mfind
morphon-0.0.8.data/scripts/mmeter
morphon-0.0.8.data/scripts/mmod
morphon-0.0.8.data/scripts/mrep
morphon-0.0.8.data/scripts/msholl
morphon-0.0.8.data/scripts/mview
morphon-0.0.8.dist-info/LICENSE
morphon-0.0.8.dist-info/METADATA
morphon-0.0.8.dist-info/WHEEL
morphon-0.0.8.dist-info/top_level.txt
morphon-0.0.8.dist-info/RECORD
